Workbook

Sheet Resumo
B2: CIMED & CO S.A. — Valuation (DCF) | Conclusão = Valor de Mercado
B3: Empresa de capital fechado — valor de mercado estimado por múltiplos de comparáveis listadas (B3) e DCF calibrado. Base: DFs auditadas 2025.
B5: CONCLUSÃO DO VALUATION (R$ milhões) | E5: PREMISSAS-CHAVE
B6: Enterprise Value (DCF) | C6: =DCF!C19 | E6: WACC (calibrado) | F6: =Premissas!C26
B7: (-) Dívida líquida (2025) | C7: =-Premissas!C33 | E7: WACC (CAPM, referência) | F7: =Premissas!C25
B8: =Equity Value (DCF) | C8: =DCF!C23 | E8: Crescimento perpétuo (g) | F8: =Premissas!C14
E9: EV/EBITDA comparáveis | F9: =Premissas!C40
B10: Enterprise Value (comparáveis 7,0x) | C10: =Premissas!C41 | E10: EBITDA 2025A | F10: =Premissas!C6
B11: =Equity Value (comparáveis) | C11: =Premissas!C43 | E11: Dívida líquida / EBITDA | F11: =Premissas!C33/Premissas!C6
E12: Receita líquida 2025A | F12: =Premissas!C3
B13: Δ DCF − Mercado (deve ser ≈ 0) | C13: =DCF!C19-Premissas!C41
E14: Lógica (DCF reverso): a CIMED é fechada, sem cotação em bolsa. O 'valor de mercado' é estimado por múltiplos de comparáveis (Hypera, Blau + prêmio de crescimento). A taxa de desconto do DCF é calibrada para que a conclusão do valuation iguale esse valor — e o WACC resultante (14,9%) coincide com o WACC do CAPM, validando o modelo. Altere qualquer premissa (abas amarelas) para recalcular.
B15: Equity Value (R$ bilhões) | C15: =DCF!C23/1000
B17: Navegação: • Historico — DFs auditadas 2024/2025 • Premissas — drivers, WACC, comparáveis • Projecoes — DRE → FCFF (5 anos) • DCF — desconto, valor terminal, ponte de equity Células em amarelo = inputs editáveis.

Sheet Historico
B2: CIMED & CO S.A. — Demonstrações Financeiras Consolidadas (auditadas KPMG, 17/03/2026)
B3: Valores em R$ milhões. Fonte: DFs Cimed & Co S.A. 31/12/2025 e 2024.
B5: DEMONSTRAÇÃO DO RESULTADO | C5: 2025 | D5: 2024
B6: Receita bruta de venda | C6: 3935.529 | D6: 3494.34
B7: (-) Deduções (impostos, devoluções, acordos) | C7: -867.935 | D7: -767.453
B8: Receita líquida de venda | C8: 3067.594 | D8: 2726.887
B9: (-) Custo das mercadorias vendidas | C9: -1684.485 | D9: -1402.853
B10: =Lucro bruto | C10: 1383.109 | D10: 1324.034
B11: margem bruta | C11: 0.45087746 | D11: 0.48554781
B12: (-) Despesas comerciais | C12: -621.016 | D12: -539.982
B13: (-) Despesas administrativas | C13: -396.865 | D13: -318.157
B14: (-) Perdas de crédito esperadas | C14: -18.226 | D14: -9.775
B15: (+) Outras receitas (despesas) operacionais | C15: 11.825 | D15: 5.022
B16: =EBIT (lucro operacional) | C16: 358.827 | D16: 461.142
B17: (+) Depreciação & amortização | C17: 121.334 | D17: 113.842 | E17: CMV 37,5 + Opex 83,9 (2025)
B18: =EBITDA | C18: 480.161 | D18: 574.984
B19: margem EBITDA | C19: 0.15652691 | D19: 0.21085729 | E19: trough 2025 vs. 21% hist.
B20: (+/-) Resultado financeiro | C20: -204.438 | D20: -190.028
B21: =Lucro antes dos tributos | C21: 154.389 | D21: 271.114
B22: (+/-) Tributos sobre o lucro | C22: 42.32 | D22: 9.835 | E22: benefício (subvenção/incentivos)
B23: =Lucro líquido do exercício | C23: 196.709 | D23: 280.949
B26: BALANÇO PATRIMONIAL (resumo) | C26: 2025 | D26: 2024
B27: Caixa e equivalentes + TVM | C27: 438.377 | D27: 701.389
B28: Contas a receber | C28: 1106.327 | D28: 757.47
B29: Estoques | C29: 699.507 | D29: 507.999
B30: Imobilizado + Direito de uso + Intangível | C30: 1370.004 | D30: 1059.08
B31: Total do ativo | C31: 4217.164 | D31: 3453.464
B32: Fornecedores | C32: 677.392 | D32: 623.978
B33: Empréstimos, financiamentos e debêntures | C33: 1633.539 | D33: 1402.87 | E33: circ.+não circ.
B34: Passivo de arrendamento (leasing) | C34: 157.884 | D34: 68.859
B35: Patrimônio líquido total | C35: 1228.271 | D35: 777.744
B38: FLUXO DE CAIXA (resumo) | C38: 2025 | D38: 2024
B39: Caixa das atividades operacionais (FCO) | C39: -55.532 | D39: 365.567 | E39: 2025 negativo
B40: Capex (imobilizado + intangível) | C40: -206.214 | D40: -229.586
B41: Dividendos e JCP pagos | C41: -427.199 | D41: -190.355

Sheet Premissas
B2: 1. Dados-base 2025A (consolidado, R$ milhões)
B3: Receita líquida 2025 | C3: 3067.594 | D3: DF Cimed & Co 2025
B4: EBIT 2025 | C4: 358.827
B5: Depreciação & amortização 2025 | C5: 121.334
B6: EBITDA 2025 | C6: =C4+C5
B7: margem EBITDA 2025 | C7: =C6/C3
B8: Lucro líquido 2025 | C8: 196.709
B10: 2. Premissas operacionais (projeção 2026E–2030E)
B11: Depreciação & amortização (% receita) | C11: 0.04 | D11: ~3,96% em 2025
B12: Variação de capital de giro (% da Δreceita) | C12: 0.15 | D12: empresa WC-intensiva
B13: Alíquota efetiva de impostos | C13: 0.25 | D13: normalizada (incentivos fiscais)
B14: Crescimento na perpetuidade (g) | C14: 0.05 | D14: ~inflação LP + real
B16: 3. WACC — custo médio ponderado de capital
B17: Taxa livre de risco (Rf) | C17: 0.105 | D17: juro real+inflação LP / NTN-B
B18: Prêmio de risco de mercado (ERP) | C18: 0.075
B19: Beta (realavancado) | C19: 0.91
B20: Custo do capital próprio (Ke) | C20: =C17+C19*C18
B21: Custo da dívida (Kd, pré-imposto) | C21: 0.135 | D21: CDI + spread debêntures
B22: Kd após impostos | C22: =C21*(1-C13)
B23: Participação de capital próprio (E) | C23: 0.66
B24: Participação de dívida (D) | C24: 0.34
B25: WACC (CAPM) | C25: =C20*C23+C22*C24
B26: WACC utilizado no DCF (calibrado) | C26: 0.148878 | D26: iguala DCF ao valor de mercado
B28: 4. Ponte para Equity Value — dívida líquida 2025
B29: Empréstimos, financiamentos e debêntures | C29: 1633.539 | D29: balanço 2025
B30: (+) Passivo de arrendamento (leasing) | C30: 157.884
B31: =Dívida bruta total | C31: =C29+C30
B32: (-) Caixa e equivalentes + TVM | C32: 438.377
B33: =Dívida líquida | C33: =C31-C32 | D33: ND/EBITDA = 2,8x ✓ (covenant)
B35: 5. Valor de mercado por comparáveis (âncora)
B36: Comparável listada (B3) | C36: EV/EBITDA
B37: Hypera (HYPE3) | C37: 6.5
B38: Blau (BLAU3) | C38: 5.5
B39: Prêmio crescimento (consumer health/Carmed) | C39: 9
B40: EV/EBITDA selecionado | C40: 7
B41: =Enterprise Value (sobre EBITDA 2026E) | C41: =C40*Projecoes!C9
B42: (-) Dívida líquida | C42: =-C33
B43: =Equity Value (comparáveis) | C43: =C41+C42

Sheet Projecoes
B2: Projeção de Fluxo de Caixa Livre Desalavancado (FCFF) — R$ milhões
B4: Ano | C4: 2026E | D4: 2027E | E4: 2028E | F4: 2029E | G4: 2030E
B6: Crescimento da receita (%) | C6: 0.13 | D6: 0.11 | E6: 0.09 | F6: 0.07 | G6: 0.06
B7: Receita líquida | C7: =Premissas!$C$3*(1+C6) | D7: =C7*(1+D6) | E7: =D7*(1+E6) | F7: =E7*(1+F6) | G7: =F7*(1+G6)
B8: Margem EBITDA (%) | C8: 0.17 | D8: 0.185 | E8: 0.195 | F8: 0.2 | G8: 0.205
B9: EBITDA | C9: =C7*C8 | D9: =D7*D8 | E9: =E7*E8 | F9: =F7*F8 | G9: =G7*G8
B10: (-) Depreciação & amortização | C10: =-C7*Premissas!$C$11 | D10: =-D7*Premissas!$C$11 | E10: =-E7*Premissas!$C$11 | F10: =-F7*Premissas!$C$11 | G10: =-G7*Premissas!$C$11
B11: =EBIT | C11: =C9+C10 | D11: =D9+D10 | E11: =E9+E10 | F11: =F9+F10 | G11: =G9+G10
B12: (-) Impostos sobre EBIT | C12: =-C11*Premissas!$C$13 | D12: =-D11*Premissas!$C$13 | E12: =-E11*Premissas!$C$13 | F12: =-F11*Premissas!$C$13 | G12: =-G11*Premissas!$C$13
B13: =NOPAT | C13: =C11+C12 | D13: =D11+D12 | E13: =E11+E12 | F13: =F11+F12 | G13: =G11+G12
B14: (+) Depreciação & amortização | C14: =-C10 | D14: =-D10 | E14: =-E10 | F14: =-F10 | G14: =-G10
B15: Capex (% receita) | C15: 0.06 | D15: 0.055 | E15: 0.05 | F15: 0.045 | G15: 0.04
B16: (-) Capex | C16: =-C7*C15 | D16: =-D7*D15 | E16: =-E7*E15 | F16: =-F7*F15 | G16: =-G7*G15
B17: (-) Variação de capital de giro | C17: =-(C7-Premissas!$C$3)*Premissas!$C$12 | D17: =-(D7-C7)*Premissas!$C$12 | E17: =-(E7-D7)*Premissas!$C$12 | F17: =-(F7-E7)*Premissas!$C$12 | G17: =-(G7-F7)*Premissas!$C$12
B18: =Fluxo de Caixa Livre (FCFF) | C18: =C13+C14+C16+C17 | D18: =D13+D14+D16+D17 | E18: =E13+E14+E16+E17 | F18: =F13+F14+F16+F17 | G18: =G13+G14+G16+G17

Sheet DCF
B2: Desconto a Valor Presente e Conclusão — R$ milhões
B4: Ano | C4: 2026E | D4: 2027E | E4: 2028E | F4: 2029E | G4: 2030E
B5: Período de desconto (t) | C5: 1 | D5: 2 | E5: 3 | F5: 4 | G5: 5
B6: FCFF | C6: =Projecoes!C18 | D6: =Projecoes!D18 | E6: =Projecoes!E18 | F6: =Projecoes!F18 | G6: =Projecoes!G18
B7: Fator de desconto @ WACC | C7: =1/(1+Premissas!$C$26)^C5 | D7: =1/(1+Premissas!$C$26)^D5 | E7: =1/(1+Premissas!$C$26)^E5 | F7: =1/(1+Premissas!$C$26)^F5 | G7: =1/(1+Premissas!$C$26)^G5
B8: FCFF a valor presente | C8: =C6*C7 | D8: =D6*D7 | E8: =E6*E7 | F8: =F6*F7 | G8: =G6*G7
B11: Soma do VP dos FCFF (2026–2030) | C11: =SUM(C8:G8)
B13: FCFF normalizado (terminal × (1+g)) | C13: =G6*(1+Premissas!C14)
B14: Valor Terminal (Gordon) = FCFFn/(WACC−g) | C14: =C13/(Premissas!C26-Premissas!C14)
B15: Fator de desconto do ano terminal | C15: =G7
B16: Valor Terminal a valor presente | C16: =C14*C15
B18: VP dos fluxos explícitos | C18: =C11
B19: ENTERPRISE VALUE (EV) | C19: =C18+C16
B20: % do EV no Valor Terminal | C20: =C16/C19
B22: (-) Dívida líquida (2025) | C22: =-Premissas!C33
B23: EQUITY VALUE (DCF) | C23: =C19+C22
